setup.py
dsnd_probability_yvs/Binomialdistribution.py
dsnd_probability_yvs/Gaussiandistribution.py
dsnd_probability_yvs/Generaldistribution.py
dsnd_probability_yvs/__init__.py
dsnd_probability_yvs.egg-info/PKG-INFO
dsnd_probability_yvs.egg-info/SOURCES.txt
dsnd_probability_yvs.egg-info/dependency_links.txt
dsnd_probability_yvs.egg-info/not-zip-safe
dsnd_probability_yvs.egg-info/top_level.txt