Metadata-Version: 1.0
Name: dsnd-probability-yvs
Version: 1.0
Summary: Gaussian and Binomial distributions
Home-page: UNKNOWN
Author: Sandeep Yerra
Author-email: sandeep.yvs@gmail.com
License: UNKNOWN
Platform: UNKNOWN
